[
  {
    "href": "/in/carmit-kirnes-90545282/"
  },
  {
    "href": "/in/carmit-kirnes-90545282/"
  },
  {
    "href": "/in/irit-even-haim-47715675/"
  },
  {
    "href": "/in/irit-even-haim-47715675/"
  },
  {
    "href": "/in/chen-amram/"
  },
  {
    "href": "/in/chen-amram/"
  },
  {
    "href": "/in/roie-almagor-ab8411146/"
  },
  {
    "href": "/in/roie-almagor-ab8411146/"
  },
  {
    "href": "/in/lilachcarmely/"
  },
  {
    "href": "/in/lilachcarmely/"
  },
  {
    "href": "/in/shani-ushki-210043102/"
  },
  {
    "href": "/in/shani-ushki-210043102/"
  },
  {
    "href": "/in/shira-beit-halachmi-cohen-bb585497/"
  },
  {
    "href": "/in/shira-beit-halachmi-cohen-bb585497/"
  },
  {
    "href": "/in/na-ama-raz-83a1a117/"
  },
  {
    "href": "/in/na-ama-raz-83a1a117/"
  },
  {
    "href": "/in/tammy-peres-keinan-47123728/"
  },
  {
    "href": "/in/tammy-peres-keinan-47123728/"
  },
  {
    "href": "/in/keren-barak-8a72b0152/"
  },
  {
    "href": "/in/keren-barak-8a72b0152/"
  },
  {
    "href": "/in/tehila-menashe-bba62b63/"
  },
  {
    "href": "/in/tehila-menashe-bba62b63/"
  },
  {
    "href": "/in/alma-london-211553113/"
  },
  {
    "href": "/in/alma-london-211553113/"
  },
  {
    "href": "/in/evgenia-gadaev-64028697/"
  },
  {
    "href": "/in/evgenia-gadaev-64028697/"
  },
  {
    "href": "/in/orel-havshush-neumann/"
  },
  {
    "href": "/in/orel-havshush-neumann/"
  },
  {
    "href": "/in/adi-fine-96271811/"
  },
  {
    "href": "/in/adi-fine-96271811/"
  },
  {
    "href": "/in/meital-altman-10179783/"
  },
  {
    "href": "/in/meital-altman-10179783/"
  },
  {
    "href": "/in/liat-klein-38391b62/"
  },
  {
    "href": "/in/liat-klein-38391b62/"
  },
  {
    "href": "/in/livnat-tahel-maimon-5069a2108/"
  },
  {
    "href": "/in/livnat-tahel-maimon-5069a2108/"
  },
  {
    "href": "/in/naama-gutraeman-54568a44/"
  },
  {
    "href": "/in/naama-gutraeman-54568a44/"
  },
  {
    "href": "/in/yael-attar-3089228a/"
  },
  {
    "href": "/in/yael-attar-3089228a/"
  },
  {
    "href": "/in/maya-sover/"
  },
  {
    "href": "/in/maya-sover/"
  },
  {
    "href": "/in/dori-joseph-6899b6108/"
  },
  {
    "href": "/in/dori-joseph-6899b6108/"
  },
  {
    "href": "/in/nufar-zioni-864ba0150/"
  },
  {
    "href": "/in/nufar-zioni-864ba0150/"
  },
  {
    "href": "/in/michalnaamanybenshabo/"
  },
  {
    "href": "/in/michalnaamanybenshabo/"
  },
  {
    "href": "/in/sonyakugel-prorecruiterhr/"
  },
  {
    "href": "/in/sonyakugel-prorecruiterhr/"
  },
  {
    "href": "/in/lital-hadad-7ab3295b/"
  },
  {
    "href": "/in/lital-hadad-7ab3295b/"
  },
  {
    "href": "/in/shirlykohai/"
  },
  {
    "href": "/in/shirlykohai/"
  },
  {
    "href": "/in/reut-mussel-2395b4156/"
  },
  {
    "href": "/in/reut-mussel-2395b4156/"
  },
  {
    "href": "/in/dafnamaron/"
  },
  {
    "href": "/in/dafnamaron/"
  },
  {
    "href": "/in/meirav-shamir-a7193416/"
  },
  {
    "href": "/in/meirav-shamir-a7193416/"
  },
  {
    "href": "/in/liron-jacobs-696167196/"
  },
  {
    "href": "/in/liron-jacobs-696167196/"
  },
  {
    "href": "/in/%E2%9C%A8neta-rushinek%F0%9F%8E%AF%F0%9F%95%B9-91a56027/"
  },
  {
    "href": "/in/%E2%9C%A8neta-rushinek%F0%9F%8E%AF%F0%9F%95%B9-91a56027/"
  },
  {
    "href": "/in/noy-manor-%E2%9C%AA-i-m-hiring-%E2%9C%AA-6620b7111/"
  },
  {
    "href": "/in/noy-manor-%E2%9C%AA-i-m-hiring-%E2%9C%AA-6620b7111/"
  },
  {
    "href": "/in/mayaroytman/"
  },
  {
    "href": "/in/mayaroytman/"
  },
  {
    "href": "/in/maya-gross-b75015187/"
  },
  {
    "href": "/in/maya-gross-b75015187/"
  },
  {
    "href": "/in/yoavhaim/"
  },
  {
    "href": "/in/yoavhaim/"
  },
  {
    "href": "/in/shahar-segal-262b55109/"
  },
  {
    "href": "/in/shahar-segal-262b55109/"
  },
  {
    "href": "/in/daniel-davidovich-6826b5185/"
  },
  {
    "href": "/in/daniel-davidovich-6826b5185/"
  },
  {
    "href": "/in/eshhrm/"
  },
  {
    "href": "/in/eshhrm/"
  },
  {
    "href": "/in/talya-goren-7b7336111/"
  },
  {
    "href": "/in/talya-goren-7b7336111/"
  },
  {
    "href": "/in/dorit-agiv-23742520/"
  },
  {
    "href": "/in/dorit-agiv-23742520/"
  },
  {
    "href": "/in/haya-shoval-0b299818/"
  },
  {
    "href": "/in/haya-shoval-0b299818/"
  },
  {
    "href": "/in/sharon-eden-6329528/"
  },
  {
    "href": "/in/sharon-eden-6329528/"
  },
  {
    "href": "/in/%E2%AD%90-shimrit-ben-aderet-%E2%AD%90-a74656122/"
  },
  {
    "href": "/in/%E2%AD%90-shimrit-ben-aderet-%E2%AD%90-a74656122/"
  },
  {
    "href": "/in/chen-moav-rolnizki-701833b3/"
  },
  {
    "href": "/in/chen-moav-rolnizki-701833b3/"
  },
  {
    "href": "/in/shirleykatztotaladmin/"
  },
  {
    "href": "/in/shirleykatztotaladmin/"
  },
  {
    "href": "/in/nofar-yanay-9051363/"
  },
  {
    "href": "/in/nofar-yanay-9051363/"
  },
  {
    "href": "/in/chen-kashash-shati-81a37ba2/"
  },
  {
    "href": "/in/chen-kashash-shati-81a37ba2/"
  },
  {
    "href": "/in/liat-amidan-man-518b4835/"
  },
  {
    "href": "/in/liat-amidan-man-518b4835/"
  },
  {
    "href": "/in/shiran-adiv-9a478a82/"
  },
  {
    "href": "/in/shiran-adiv-9a478a82/"
  },
  {
    "href": "/in/alinakulichkova/"
  },
  {
    "href": "/in/alinakulichkova/"
  },
  {
    "href": "/in/pazit-matityahu/"
  },
  {
    "href": "/in/pazit-matityahu/"
  },
  {
    "href": "/in/liat-shiffman-26a4a353/"
  },
  {
    "href": "/in/liat-shiffman-26a4a353/"
  },
  {
    "href": "/in/daniel-barokas-26ba20141/"
  },
  {
    "href": "/in/daniel-barokas-26ba20141/"
  },
  {
    "href": "/in/hadas-segev-i-m-hiring-34224970/"
  },
  {
    "href": "/in/hadas-segev-i-m-hiring-34224970/"
  },
  {
    "href": "/in/maayanamir/"
  },
  {
    "href": "/in/maayanamir/"
  },
  {
    "href": "/in/shiran-nagar-631333119/"
  },
  {
    "href": "/in/shiran-nagar-631333119/"
  },
  {
    "href": "/in/mor-ovadia-83825128/"
  },
  {
    "href": "/in/mor-ovadia-83825128/"
  },
  {
    "href": "/in/ravitorenphd/"
  },
  {
    "href": "/in/ravitorenphd/"
  },
  {
    "href": "/in/avigail-godinger-52995123/"
  },
  {
    "href": "/in/avigail-godinger-52995123/"
  },
  {
    "href": "/in/orittwingo/"
  },
  {
    "href": "/in/orittwingo/"
  },
  {
    "href": "/in/shira-berkovitch-fromchenko-a44b7126/"
  },
  {
    "href": "/in/shira-berkovitch-fromchenko-a44b7126/"
  },
  {
    "href": "/in/mayakoren/"
  },
  {
    "href": "/in/mayakoren/"
  },
  {
    "href": "/in/sivan-eliyahu-43559245/"
  },
  {
    "href": "/in/sivan-eliyahu-43559245/"
  },
  {
    "href": "/in/nofar-ben-moies-271358a8/"
  },
  {
    "href": "/in/nofar-ben-moies-271358a8/"
  },
  {
    "href": "/in/shiraga42711a75/"
  },
  {
    "href": "/in/shiraga42711a75/"
  },
  {
    "href": "/in/ron-mangadi-579b9010b/"
  },
  {
    "href": "/in/ron-mangadi-579b9010b/"
  },
  {
    "href": "/in/shirel-moshe-12737989/"
  },
  {
    "href": "/in/shirel-moshe-12737989/"
  },
  {
    "href": "/in/orbarcohen/"
  },
  {
    "href": "/in/orbarcohen/"
  },
  {
    "href": "/in/hofit-topper-7923728b/"
  },
  {
    "href": "/in/hofit-topper-7923728b/"
  },
  {
    "href": "/in/michal-klein-289415123/"
  },
  {
    "href": "/in/michal-klein-289415123/"
  },
  {
    "href": "/in/gal-adriana-tarchitzky-9570585b/"
  },
  {
    "href": "/in/gal-adriana-tarchitzky-9570585b/"
  },
  {
    "href": "/in/adi-zamir7474/"
  },
  {
    "href": "/in/adi-zamir7474/"
  },
  {
    "href": "/in/maya-skliar-17281494/"
  },
  {
    "href": "/in/maya-skliar-17281494/"
  },
  {
    "href": "/in/bellabangayev/"
  },
  {
    "href": "/in/bellabangayev/"
  },
  {
    "href": "/in/hila-haba-1805949/"
  },
  {
    "href": "/in/hila-haba-1805949/"
  },
  {
    "href": "/in/roni-avrahami-28492672/"
  },
  {
    "href": "/in/roni-avrahami-28492672/"
  },
  {
    "href": "/in/liatkatzbenmoshe/"
  },
  {
    "href": "/in/liatkatzbenmoshe/"
  },
  {
    "href": "/in/ornadreman/"
  },
  {
    "href": "/in/ornadreman/"
  },
  {
    "href": "/in/dana-yaron-schwarts/"
  },
  {
    "href": "/in/dana-yaron-schwarts/"
  },
  {
    "href": "/in/udi-itzhayek-4387b/"
  },
  {
    "href": "/in/udi-itzhayek-4387b/"
  },
  {
    "href": "/in/shiran-parag/"
  },
  {
    "href": "/in/shiran-parag/"
  },
  {
    "href": "/in/mordavid/"
  },
  {
    "href": "/in/mordavid/"
  },
  {
    "href": "/in/irishanania/"
  },
  {
    "href": "/in/irishanania/"
  },
  {
    "href": "/in/shimrit-eitan-94292a91/"
  },
  {
    "href": "/in/shimrit-eitan-94292a91/"
  },
  {
    "href": "/in/sharon-srugo-7bb637164/"
  },
  {
    "href": "/in/sharon-srugo-7bb637164/"
  },
  {
    "href": "/in/adi-perelman-solomon-b8705a77/"
  },
  {
    "href": "/in/adi-perelman-solomon-b8705a77/"
  },
  {
    "href": "/in/anat-artzi-a0a27b1a/"
  },
  {
    "href": "/in/anat-artzi-a0a27b1a/"
  },
  {
    "href": "/in/angelina-vovk-244871127/"
  },
  {
    "href": "/in/angelina-vovk-244871127/"
  },
  {
    "href": "/in/shiri-kontes-gilgun-058a6737/"
  },
  {
    "href": "/in/shiri-kontes-gilgun-058a6737/"
  },
  {
    "href": "/in/miran-alon-5b6952149/"
  },
  {
    "href": "/in/miran-alon-5b6952149/"
  },
  {
    "href": "/in/coralboani/"
  },
  {
    "href": "/in/coralboani/"
  },
  {
    "href": "/in/marina-herzberg-ab005522/"
  },
  {
    "href": "/in/marina-herzberg-ab005522/"
  },
  {
    "href": "/in/tal-werbner-%D7%98%D7%9C-%D7%95%D7%A8%D7%91%D7%A0%D7%A8-62a385b1/"
  },
  {
    "href": "/in/tal-werbner-%D7%98%D7%9C-%D7%95%D7%A8%D7%91%D7%A0%D7%A8-62a385b1/"
  },
  {
    "href": "/in/elisheva-levitan-22313698/"
  },
  {
    "href": "/in/elisheva-levitan-22313698/"
  },
  {
    "href": "/in/ilana-ben-yishay-850a5315/"
  },
  {
    "href": "/in/ilana-ben-yishay-850a5315/"
  },
  {
    "href": "/in/ronen-daniel-5922b3128/"
  },
  {
    "href": "/in/ronen-daniel-5922b3128/"
  },
  {
    "href": "/in/shay-rotem-5976a582/"
  },
  {
    "href": "/in/shay-rotem-5976a582/"
  },
  {
    "href": "/in/danielle-creation-group-954739152/"
  },
  {
    "href": "/in/danielle-creation-group-954739152/"
  },
  {
    "href": "/in/alisa-noy-b7904a9/"
  },
  {
    "href": "/in/alisa-noy-b7904a9/"
  },
  {
    "href": "/in/noam-bar-%E2%98%85i-m-hiring%E2%98%85-023539199/"
  },
  {
    "href": "/in/noam-bar-%E2%98%85i-m-hiring%E2%98%85-023539199/"
  },
  {
    "href": "/in/heidi-e-966013148/"
  },
  {
    "href": "/in/heidi-e-966013148/"
  },
  {
    "href": "/in/viki-mizrahi-aa52a1145/"
  },
  {
    "href": "/in/viki-mizrahi-aa52a1145/"
  },
  {
    "href": "/in/keren-weinberg-ofir-a0568b100/"
  },
  {
    "href": "/in/keren-weinberg-ofir-a0568b100/"
  },
  {
    "href": "/in/daniela-yegudayev/"
  },
  {
    "href": "/in/daniela-yegudayev/"
  },
  {
    "href": "/in/keren-aharon-720b45a5/"
  },
  {
    "href": "/in/keren-aharon-720b45a5/"
  },
  {
    "href": "/in/yasmin-edlan-7645b5163/"
  },
  {
    "href": "/in/yasmin-edlan-7645b5163/"
  },
  {
    "href": "/in/tali-loven-7ba6b259/"
  },
  {
    "href": "/in/tali-loven-7ba6b259/"
  },
  {
    "href": "/in/liat-darsa-levin-a928a95a/"
  },
  {
    "href": "/in/liat-darsa-levin-a928a95a/"
  },
  {
    "href": "/in/objectivec/"
  },
  {
    "href": "/in/objectivec/"
  },
  {
    "href": "/in/dana-israeli-a1804b149/"
  },
  {
    "href": "/in/dana-israeli-a1804b149/"
  },
  {
    "href": "/in/alona-ashkenazi/"
  },
  {
    "href": "/in/alona-ashkenazi/"
  },
  {
    "href": "/in/tal-weizman-rosenthal-358447153/"
  },
  {
    "href": "/in/tal-weizman-rosenthal-358447153/"
  },
  {
    "href": "/in/sarit-malka-liberman-0b147b6/"
  },
  {
    "href": "/in/sarit-malka-liberman-0b147b6/"
  },
  {
    "href": "/in/einat-salemnick-b5992360/"
  },
  {
    "href": "/in/einat-salemnick-b5992360/"
  },
  {
    "href": "/in/michal-gerson-45a687/"
  },
  {
    "href": "/in/michal-gerson-45a687/"
  },
  {
    "href": "/in/dana-ben-yosef/"
  },
  {
    "href": "/in/dana-ben-yosef/"
  },
  {
    "href": "/in/hadar-eyal-7a78697b/"
  },
  {
    "href": "/in/hadar-eyal-7a78697b/"
  },
  {
    "href": "/in/chen-navon-9196148/"
  },
  {
    "href": "/in/chen-navon-9196148/"
  },
  {
    "href": "/in/liat-rozen-a5778060/"
  },
  {
    "href": "/in/liat-rozen-a5778060/"
  },
  {
    "href": "/in/lital-haron-8a5922119/"
  },
  {
    "href": "/in/lital-haron-8a5922119/"
  },
  {
    "href": "/in/shirandudaee/"
  },
  {
    "href": "/in/shirandudaee/"
  },
  {
    "href": "/in/yaaramalul/"
  },
  {
    "href": "/in/yaaramalul/"
  },
  {
    "href": "/in/inbal-bar-sinay-a63a0640/"
  },
  {
    "href": "/in/inbal-bar-sinay-a63a0640/"
  },
  {
    "href": "/in/iris-sela-936661106/"
  },
  {
    "href": "/in/iris-sela-936661106/"
  },
  {
    "href": "/in/noam-gershoni/"
  },
  {
    "href": "/in/noam-gershoni/"
  },
  {
    "href": "/in/elin-gofman-%E2%98%85i-m-hiring%E2%98%85-544a0b107/"
  },
  {
    "href": "/in/elin-gofman-%E2%98%85i-m-hiring%E2%98%85-544a0b107/"
  },
  {
    "href": "/in/dikla-levy-9656b16/"
  },
  {
    "href": "/in/dikla-levy-9656b16/"
  },
  {
    "href": "/in/veredyaloz/"
  },
  {
    "href": "/in/veredyaloz/"
  },
  {
    "href": "/in/shir-weiss-15276810b/"
  },
  {
    "href": "/in/shir-weiss-15276810b/"
  },
  {
    "href": "/in/efrat-assaraf-segelman-312b4a29/"
  },
  {
    "href": "/in/efrat-assaraf-segelman-312b4a29/"
  },
  {
    "href": "/in/sandra-lechtman-strauss-98a60796/"
  },
  {
    "href": "/in/sandra-lechtman-strauss-98a60796/"
  },
  {
    "href": "/in/maya-levi-malka-a66b9915/"
  },
  {
    "href": "/in/maya-levi-malka-a66b9915/"
  },
  {
    "href": "/in/shira-ohana-99a6a8186/"
  },
  {
    "href": "/in/shira-ohana-99a6a8186/"
  },
  {
    "href": "/in/lital-eitan-shmidet-53007340/"
  },
  {
    "href": "/in/lital-eitan-shmidet-53007340/"
  },
  {
    "href": "/in/ewafokin/"
  },
  {
    "href": "/in/ewafokin/"
  },
  {
    "href": "/in/lironbinyamin/"
  },
  {
    "href": "/in/lironbinyamin/"
  },
  {
    "href": "/in/tslil-shilinger-16b7aa67/"
  },
  {
    "href": "/in/tslil-shilinger-16b7aa67/"
  },
  {
    "href": "/in/elena-kadosh-573753155/"
  },
  {
    "href": "/in/elena-kadosh-573753155/"
  },
  {
    "href": "/in/dganit-haviv/"
  },
  {
    "href": "/in/dganit-haviv/"
  },
  {
    "href": "/in/adva-argov-7706194b/"
  },
  {
    "href": "/in/adva-argov-7706194b/"
  },
  {
    "href": "/in/rotemassaf/"
  },
  {
    "href": "/in/rotemassaf/"
  },
  {
    "href": "/in/sivan-hason-72a72b49/"
  },
  {
    "href": "/in/sivan-hason-72a72b49/"
  },
  {
    "href": "/in/orly-shemesh-regev-0a531254/"
  },
  {
    "href": "/in/orly-shemesh-regev-0a531254/"
  },
  {
    "href": "/in/tzipi-kassif-a19503ab/"
  },
  {
    "href": "/in/tzipi-kassif-a19503ab/"
  },
  {
    "href": "/in/ortalnatanzen/"
  },
  {
    "href": "/in/ortalnatanzen/"
  },
  {
    "href": "/in/michal-eyal-1b112a102/"
  },
  {
    "href": "/in/michal-eyal-1b112a102/"
  },
  {
    "href": "/in/or-ezra-%D7%90%D7%95%D7%A8-%D7%A2%D7%96%D7%A8%D7%90-0b3553127/"
  },
  {
    "href": "/in/or-ezra-%D7%90%D7%95%D7%A8-%D7%A2%D7%96%D7%A8%D7%90-0b3553127/"
  },
  {
    "href": "/in/tahlwilsonhr/"
  },
  {
    "href": "/in/tahlwilsonhr/"
  },
  {
    "href": "/in/hilla-grimberg/"
  },
  {
    "href": "/in/hilla-grimberg/"
  },
  {
    "href": "/in/din-klainer-%E2%9C%AAi-m-hiring%E2%9C%AA-aaa344131/"
  },
  {
    "href": "/in/din-klainer-%E2%9C%AAi-m-hiring%E2%9C%AA-aaa344131/"
  },
  {
    "href": "/in/lital-kaneti-2b3150126/"
  },
  {
    "href": "/in/lital-kaneti-2b3150126/"
  },
  {
    "href": "/in/daniela-zvi-933804116/"
  },
  {
    "href": "/in/daniela-zvi-933804116/"
  },
  {
    "href": "/in/ayelet-tauber-037a27141/"
  },
  {
    "href": "/in/ayelet-tauber-037a27141/"
  },
  {
    "href": "/in/adi-kuperly-71112ab9/"
  },
  {
    "href": "/in/adi-kuperly-71112ab9/"
  },
  {
    "href": "/in/noa-bargill-49494982/"
  },
  {
    "href": "/in/noa-bargill-49494982/"
  },
  {
    "href": "/in/maya-gross-cyber-jobs-8484a0192/"
  },
  {
    "href": "/in/maya-gross-cyber-jobs-8484a0192/"
  },
  {
    "href": "/in/anna-axelrod-57960210a/"
  },
  {
    "href": "/in/anna-axelrod-57960210a/"
  },
  {
    "href": "/in/ifat-kahan/"
  },
  {
    "href": "/in/ifat-kahan/"
  },
  {
    "href": "/in/carmit-shlush-einhorn-9058327/"
  },
  {
    "href": "/in/carmit-shlush-einhorn-9058327/"
  },
  {
    "href": "/in/michal-zamir-87ab13109/"
  },
  {
    "href": "/in/michal-zamir-87ab13109/"
  },
  {
    "href": "/in/nofar-bashiri/"
  },
  {
    "href": "/in/nofar-bashiri/"
  },
  {
    "href": "/in/luda-korchevnik-2b851070/"
  },
  {
    "href": "/in/luda-korchevnik-2b851070/"
  },
  {
    "href": "/in/morit-drori/"
  },
  {
    "href": "/in/morit-drori/"
  },
  {
    "href": "/in/dorin-david-82979a61/"
  },
  {
    "href": "/in/dorin-david-82979a61/"
  },
  {
    "href": "/in/yaelkolik/"
  },
  {
    "href": "/in/yaelkolik/"
  },
  {
    "href": "/in/olga-berger-hr/"
  },
  {
    "href": "/in/olga-berger-hr/"
  },
  {
    "href": "/in/shahaf-ellenbogen/"
  },
  {
    "href": "/in/shahaf-ellenbogen/"
  },
  {
    "href": "/in/reut-reuveni-7a434276/"
  },
  {
    "href": "/in/reut-reuveni-7a434276/"
  },
  {
    "href": "/in/enbal-ben-shimon-%E2%98%85hiring-now%E2%98%85-715170112/"
  },
  {
    "href": "/in/enbal-ben-shimon-%E2%98%85hiring-now%E2%98%85-715170112/"
  },
  {
    "href": "/in/may-shoham-a28bb0164/"
  },
  {
    "href": "/in/may-shoham-a28bb0164/"
  },
  {
    "href": "/in/regina-bromberg-a4981563/"
  },
  {
    "href": "/in/regina-bromberg-a4981563/"
  },
  {
    "href": "/in/meital-solomon/"
  },
  {
    "href": "/in/meital-solomon/"
  },
  {
    "href": "/in/adi-cohen-60593113b/"
  },
  {
    "href": "/in/adi-cohen-60593113b/"
  },
  {
    "href": "/in/maya-lewandowski-25ba3048/"
  },
  {
    "href": "/in/maya-lewandowski-25ba3048/"
  },
  {
    "href": "/in/guy-sagi/"
  },
  {
    "href": "/in/guy-sagi/"
  },
  {
    "href": "/in/eti-liberzon/"
  },
  {
    "href": "/in/eti-liberzon/"
  },
  {
    "href": "/in/taly-ben-yair-4b5762a7/"
  },
  {
    "href": "/in/taly-ben-yair-4b5762a7/"
  },
  {
    "href": "/in/suzymerchav/"
  },
  {
    "href": "/in/suzymerchav/"
  },
  {
    "href": "/in/yaelcohen11/"
  },
  {
    "href": "/in/yaelcohen11/"
  },
  {
    "href": "/in/sivan-malchi-%D7%A1%D7%99%D7%95%D7%9F-%D7%9E%D7%9C%D7%97%D7%99-6952746/"
  },
  {
    "href": "/in/sivan-malchi-%D7%A1%D7%99%D7%95%D7%9F-%D7%9E%D7%9C%D7%97%D7%99-6952746/"
  },
  {
    "href": "/in/kineret-friedman-8699243b/"
  },
  {
    "href": "/in/kineret-friedman-8699243b/"
  },
  {
    "href": "/in/shlomit-cohen-lebovich-%E2%9C%AA-im-hiring-%E2%9C%AA-4a0504aa/"
  },
  {
    "href": "/in/shlomit-cohen-lebovich-%E2%9C%AA-im-hiring-%E2%9C%AA-4a0504aa/"
  },
  {
    "href": "/in/lihi-prager-9b905a118/"
  },
  {
    "href": "/in/lihi-prager-9b905a118/"
  },
  {
    "href": "/in/idit-covalio-eliaz-40288a19/"
  },
  {
    "href": "/in/idit-covalio-eliaz-40288a19/"
  },
  {
    "href": "/in/ester-shapira-705a78a4/"
  },
  {
    "href": "/in/ester-shapira-705a78a4/"
  },
  {
    "href": "/in/cohavnir/"
  },
  {
    "href": "/in/cohavnir/"
  },
  {
    "href": "/in/liron-ripp-3ba176110/"
  },
  {
    "href": "/in/liron-ripp-3ba176110/"
  },
  {
    "href": "/in/limor-peretz-mograbi-b5713256/"
  },
  {
    "href": "/in/limor-peretz-mograbi-b5713256/"
  },
  {
    "href": "/in/mennie-czeisler-25618971/"
  },
  {
    "href": "/in/mennie-czeisler-25618971/"
  },
  {
    "href": "/in/ela-bloom-916020137/"
  },
  {
    "href": "/in/ela-bloom-916020137/"
  },
  {
    "href": "/in/yael-meirson-5430b032/"
  },
  {
    "href": "/in/yael-meirson-5430b032/"
  },
  {
    "href": "/in/asaf-vexler-14b789a9/"
  },
  {
    "href": "/in/asaf-vexler-14b789a9/"
  },
  {
    "href": "/in/shirly-yekutiel-75054310/"
  },
  {
    "href": "/in/shirly-yekutiel-75054310/"
  },
  {
    "href": "/in/dafna-noy/"
  },
  {
    "href": "/in/dafna-noy/"
  },
  {
    "href": "/in/rona-kushnir-alaluf-4287b055/"
  },
  {
    "href": "/in/rona-kushnir-alaluf-4287b055/"
  },
  {
    "href": "/in/efratlavie/"
  },
  {
    "href": "/in/efratlavie/"
  },
  {
    "href": "/in/itai-alzaradel-a21257133/"
  },
  {
    "href": "/in/itai-alzaradel-a21257133/"
  },
  {
    "href": "/in/paula-goldberg/"
  },
  {
    "href": "/in/paula-goldberg/"
  },
  {
    "href": "/in/tamarkariti/"
  },
  {
    "href": "/in/tamarkariti/"
  },
  {
    "href": "/in/hadar-fuchs-%E2%98%85-i-m-hiring-%E2%98%85-90ba97116/"
  },
  {
    "href": "/in/hadar-fuchs-%E2%98%85-i-m-hiring-%E2%98%85-90ba97116/"
  },
  {
    "href": "/in/michal-ayalon-0682aa12/"
  },
  {
    "href": "/in/michal-ayalon-0682aa12/"
  },
  {
    "href": "/in/reut-arbel-i-m-hiring-44170052/"
  },
  {
    "href": "/in/reut-arbel-i-m-hiring-44170052/"
  },
  {
    "href": "/in/sarit-glas-94639929/"
  },
  {
    "href": "/in/sarit-glas-94639929/"
  },
  {
    "href": "/in/sitvanitkustka/"
  },
  {
    "href": "/in/sitvanitkustka/"
  },
  {
    "href": "/in/rachel-peretz-b86a5583/"
  },
  {
    "href": "/in/rachel-peretz-b86a5583/"
  },
  {
    "href": "/in/netakaplan/"
  },
  {
    "href": "/in/netakaplan/"
  },
  {
    "href": "/in/inbal-shkolnik-7714b3127/"
  },
  {
    "href": "/in/inbal-shkolnik-7714b3127/"
  },
  {
    "href": "/in/victoria-aronov-04ab288b/"
  },
  {
    "href": "/in/victoria-aronov-04ab288b/"
  },
  {
    "href": "/in/inbalchiat/"
  },
  {
    "href": "/in/inbalchiat/"
  },
  {
    "href": "/in/adi-shtimler-948836156/"
  },
  {
    "href": "/in/adi-shtimler-948836156/"
  },
  {
    "href": "/in/chanan-rhein-004570100/"
  },
  {
    "href": "/in/chanan-rhein-004570100/"
  },
  {
    "href": "/in/mor-zussman-289615135/"
  },
  {
    "href": "/in/mor-zussman-289615135/"
  },
  {
    "href": "/in/tal-barak-158901154/"
  },
  {
    "href": "/in/tal-barak-158901154/"
  },
  {
    "href": "/in/or-schwartz-klein-a9a6a482/"
  },
  {
    "href": "/in/or-schwartz-klein-a9a6a482/"
  },
  {
    "href": "/in/shaylavy/"
  },
  {
    "href": "/in/shaylavy/"
  },
  {
    "href": "/in/leahgid/"
  },
  {
    "href": "/in/leahgid/"
  },
  {
    "href": "/in/moran-eidlman-3018b7108/"
  },
  {
    "href": "/in/moran-eidlman-3018b7108/"
  },
  {
    "href": "/in/yarden-katz-abramovich-07926a60/"
  },
  {
    "href": "/in/yarden-katz-abramovich-07926a60/"
  },
  {
    "href": "/in/talbetter/"
  },
  {
    "href": "/in/talbetter/"
  },
  {
    "href": "/in/neta-atzmon-10a4b8139/"
  },
  {
    "href": "/in/neta-atzmon-10a4b8139/"
  },
  {
    "href": "/in/liron-segev-20b72b28/"
  },
  {
    "href": "/in/liron-segev-20b72b28/"
  },
  {
    "href": "/in/liron-kedem-27413533/"
  },
  {
    "href": "/in/liron-kedem-27413533/"
  },
  {
    "href": "/in/shanikotzer/"
  },
  {
    "href": "/in/shanikotzer/"
  },
  {
    "href": "/in/maayan-bornovsky-63a908133/"
  },
  {
    "href": "/in/maayan-bornovsky-63a908133/"
  },
  {
    "href": "/in/michalgur/"
  },
  {
    "href": "/in/michalgur/"
  },
  {
    "href": "/in/carmitbaur/"
  },
  {
    "href": "/in/carmitbaur/"
  },
  {
    "href": "/in/revital-lavi-%E2%9C%AA-49519363/"
  },
  {
    "href": "/in/revital-lavi-%E2%9C%AA-49519363/"
  },
  {
    "href": "/in/tal-gil-8281b115b/"
  },
  {
    "href": "/in/tal-gil-8281b115b/"
  },
  {
    "href": "/in/dana-levy-6015593a/"
  },
  {
    "href": "/in/dana-levy-6015593a/"
  },
  {
    "href": "/in/noapolak/"
  },
  {
    "href": "/in/noapolak/"
  },
  {
    "href": "/in/michalgoldberg1/"
  },
  {
    "href": "/in/michalgoldberg1/"
  },
  {
    "href": "/in/ariel-avital-70b1a317/"
  },
  {
    "href": "/in/ariel-avital-70b1a317/"
  },
  {
    "href": "/in/gat-shenhav-b26356104/"
  },
  {
    "href": "/in/gat-shenhav-b26356104/"
  },
  {
    "href": "/in/varditgurarie/"
  },
  {
    "href": "/in/varditgurarie/"
  },
  {
    "href": "/in/rebecca-moses-hr/"
  },
  {
    "href": "/in/rebecca-moses-hr/"
  },
  {
    "href": "/in/tamar-dekel-a4988747/"
  },
  {
    "href": "/in/tamar-dekel-a4988747/"
  },
  {
    "href": "/in/liat-shaharabany-ziv-830a652b/"
  },
  {
    "href": "/in/liat-shaharabany-ziv-830a652b/"
  },
  {
    "href": "/in/keren-arazi-48b68b44/"
  },
  {
    "href": "/in/keren-arazi-48b68b44/"
  },
  {
    "href": "/in/lee-amiga-270091137/"
  },
  {
    "href": "/in/lee-amiga-270091137/"
  },
  {
    "href": "/in/moshik-oz-89a07673/"
  },
  {
    "href": "/in/moshik-oz-89a07673/"
  },
  {
    "href": "/in/tamar-kaptowsky/"
  },
  {
    "href": "/in/tamar-kaptowsky/"
  },
  {
    "href": "/in/shiran-farchan-azimut/"
  },
  {
    "href": "/in/shiran-farchan-azimut/"
  },
  {
    "href": "/in/miri-shemesh-katz-52000255/"
  },
  {
    "href": "/in/miri-shemesh-katz-52000255/"
  },
  {
    "href": "/in/limor-rubinstein-%D7%9C%D7%99%D7%9E%D7%95%D7%A8-%D7%A8%D7%95%D7%91%D7%99%D7%A0%D7%A9%D7%98%D7%99%D7%99%D7%9F-643547a/"
  },
  {
    "href": "/in/limor-rubinstein-%D7%9C%D7%99%D7%9E%D7%95%D7%A8-%D7%A8%D7%95%D7%91%D7%99%D7%A0%D7%A9%D7%98%D7%99%D7%99%D7%9F-643547a/"
  },
  {
    "href": "/in/gilaeliyahu/"
  },
  {
    "href": "/in/gilaeliyahu/"
  },
  {
    "href": "/in/bar-slutzky-43b292147/"
  },
  {
    "href": "/in/bar-slutzky-43b292147/"
  },
  {
    "href": "/in/alice-givati-ya-akobov-211411134/"
  },
  {
    "href": "/in/alice-givati-ya-akobov-211411134/"
  },
  {
    "href": "/in/narjes-abdalhady/"
  },
  {
    "href": "/in/narjes-abdalhady/"
  },
  {
    "href": "/in/larisa-mogilevsky-90935933/"
  },
  {
    "href": "/in/larisa-mogilevsky-90935933/"
  }
]