[
  {
    "href": "/in/shira-lotan-1ab63718a/"
  },
  {
    "href": "/in/danielle-yogev-i-m-hiring-a43643104/"
  },
  {
    "href": "/in/efrat-dagan-i-m-hiring-40b6831/"
  },
  {
    "href": "/in/raisa-volnik-21891619/"
  },
  {
    "href": "/in/nava-avraham-680a163/"
  },
  {
    "href": "/in/sigal-dichter-a6988354/"
  },
  {
    "href": "/in/shlomit-greenfeld-bash-9a283ab7/"
  },
  {
    "href": "/in/michal-weiss-froelich-5aa27a45/"
  },
  {
    "href": "/in/shiran-jan-b4316823/"
  },
  {
    "href": "/in/ruti-shachar-zarifi/"
  },
  {
    "href": "/in/paz-zimroni-a847822b/"
  },
  {
    "href": "/in/sivan-shaltiel-77600974/"
  },
  {
    "href": "/in/perlitperetz/"
  },
  {
    "href": "/in/danielle-feingold-2591a0116/"
  },
  {
    "href": "/in/adi-ingber-6a7a2359/"
  },
  {
    "href": "/in/noam-paneth-640835b7/"
  },
  {
    "href": "/in/orit-berman-b9746541/"
  },
  {
    "href": "/in/shiri-mor-7054499/"
  },
  {
    "href": "/in/rona-greifner-44948589/"
  },
  {
    "href": "/in/sara-raski-98846399/"
  },
  {
    "href": "/in/agustina-fern%C3%A1ndez-29717812a/"
  },
  {
    "href": "/in/alex-voihansky-33670051/"
  },
  {
    "href": "/in/reut-ben-arosh-11b682138/"
  },
  {
    "href": "/in/niritprivman/"
  },
  {
    "href": "/in/sharoni-michaeli-34420851/"
  },
  {
    "href": "/in/revital-aharoni-1503aba2/"
  },
  {
    "href": "/in/tal-shiri-borovsky-807aa388/"
  },
  {
    "href": "/in/inga-boyangou-352bb5128/"
  },
  {
    "href": "/in/anat-rozenbaum-keren-889ba321/"
  },
  {
    "href": "/in/margaretzaitsev/"
  },
  {
    "href": "/in/adi-reiter/"
  },
  {
    "href": "/in/yulia-merkulovich/"
  },
  {
    "href": "/in/yael-schneider-00701211/"
  },
  {
    "href": "/in/linaveh/"
  },
  {
    "href": "/in/tal-debi-36290a107/"
  },
  {
    "href": "/in/nofar-baruch-518673105/"
  },
  {
    "href": "/in/avishag-eliyahu-21923a33/"
  },
  {
    "href": "/in/shani-shlomo-05805216/"
  },
  {
    "href": "/in/neta-li-nor%C3%A9n-zach-858b8a30/"
  },
  {
    "href": "/in/soniashmerling/"
  },
  {
    "href": "/in/korin-keshet-a1b05b33/"
  },
  {
    "href": "/in/adi-oren-aa7559140/"
  },
  {
    "href": "/in/smadarhopeyannai/"
  },
  {
    "href": "/in/orit-aizik-63644a155/"
  },
  {
    "href": "/in/lironovadia/"
  },
  {
    "href": "/in/yael-tarnerozky-259843110/"
  },
  {
    "href": "/in/nirit-ben-ami-305a48108/"
  },
  {
    "href": "/in/rita-luria-26677279/"
  },
  {
    "href": "/in/nataly-l-ab81828b/"
  },
  {
    "href": "/in/danielle-udelsman-%E2%98%85i-m-hiring%E2%98%85-5b2b92145/"
  },
  {
    "href": "/in/nitzanron/"
  },
  {
    "href": "/in/hadar-shochat-2b095a39/"
  },
  {
    "href": "/in/maya-toren-49169a14a/"
  },
  {
    "href": "/in/yaara-fatael-%E2%9C%AA-i-m-hiring-%E2%9C%AA-85165b122/"
  },
  {
    "href": "/in/hodaya-mor-937549a2/"
  },
  {
    "href": "/in/noa-szlapfer-055b3073/"
  },
  {
    "href": "/in/shiran-saragani-27b888178/"
  },
  {
    "href": "/in/morkedar/"
  },
  {
    "href": "/in/liat-stolero-levitzedek-a6b12a77/"
  },
  {
    "href": "/in/adi-barina-a35647106/"
  },
  {
    "href": "/in/ifat-krieger-58676a13b/"
  },
  {
    "href": "/in/polina-peretz-sofron-a4374a10b/"
  },
  {
    "href": "/in/shir-shaul/"
  },
  {
    "href": "/in/keren-malka-718b1426/"
  },
  {
    "href": "/in/yahav-cataife-40564847/"
  },
  {
    "href": "/in/liron-leibovich-gronich-83a6b517/"
  },
  {
    "href": "/in/gal-danino-startica-i-m-hiring-ba09b2a7/"
  },
  {
    "href": "/in/eden-eldan/"
  },
  {
    "href": "/in/keren-valer-4526b37/"
  },
  {
    "href": "/in/dinahr/"
  },
  {
    "href": "/in/dana-riklis-97b56057/"
  },
  {
    "href": "/in/inbarashur/"
  },
  {
    "href": "/in/liatkurlender/"
  },
  {
    "href": "/in/chen-cohen4/"
  },
  {
    "href": "/in/gal-harari-2b8b7a45/"
  },
  {
    "href": "/in/dananudel/"
  },
  {
    "href": "/in/liran-nisman-1a88772b/"
  },
  {
    "href": "/in/efrat-ya-ari-cohen-3657576a/"
  },
  {
    "href": "/in/revital-eilat-a77213178/"
  },
  {
    "href": "/in/adi-parnass-301a92a2/"
  },
  {
    "href": "/in/meitalkaitz/"
  },
  {
    "href": "/in/saritmarciano/"
  },
  {
    "href": "/in/ido-efroni-804b3650/"
  },
  {
    "href": "/in/keren-klayer-0373667/"
  },
  {
    "href": "/in/shani-shimshon-8149b520/"
  },
  {
    "href": "/in/dana-sharvit-%E2%9C%B0-i-m-hiring-9589a4159/"
  },
  {
    "href": "/in/neta-komemi-%D7%A7%D7%95%D7%9E%D7%9E%D7%99-%D7%A0%D7%98%D7%A2-a4268617/"
  },
  {
    "href": "/in/shahar-keyvan-546320104/"
  },
  {
    "href": "/in/amit-rapaport-5a8b1142/"
  },
  {
    "href": "/in/oded-weiss-15688584/"
  },
  {
    "href": "/in/lior-raizman-625695100/"
  },
  {
    "href": "/in/advacohen/"
  },
  {
    "href": "/in/tze-ela-sadeh-madmoni-0159a4123/"
  },
  {
    "href": "/in/shiran-gutman-5966698a/"
  },
  {
    "href": "/in/yifatbaron/"
  },
  {
    "href": "/in/yana-kuryliuk-0468348b/"
  },
  {
    "href": "/in/camila-budman/"
  },
  {
    "href": "/in/shiranaviram/"
  },
  {
    "href": "/in/maayan-melamed-7b860643/"
  },
  {
    "href": "/in/sarit-eyal-ba279922/"
  },
  {
    "href": "/in/karin-revivo-lavi-07311b6b/"
  },
  {
    "href": "/in/nira-e-379ab5109/"
  },
  {
    "href": "/in/irit-peleg-9a319088/"
  },
  {
    "href": "/in/ilanrozenblum/"
  },
  {
    "href": "/in/aliya-laniado-%D7%9C%D7%A0%D7%99%D7%90%D7%93%D7%95-%D7%A2%D7%9C%D7%99%D7%94-69410b64/"
  },
  {
    "href": "/in/danit-shlomi-61966511a/"
  },
  {
    "href": "/in/chen-galya-cohen-634b879b/"
  },
  {
    "href": "/in/yuli-kaganovich-066697186/"
  },
  {
    "href": "/in/ronit-hirsch-49710214/"
  },
  {
    "href": "/in/einat-j-a208301a/"
  },
  {
    "href": "/in/yael-bar-shem-1210915b/"
  },
  {
    "href": "/in/zeev-roth-81429110/"
  },
  {
    "href": "/in/ortal-dobovicz-5801b448/"
  },
  {
    "href": "/in/ayelet-orgad/"
  },
  {
    "href": "/in/daniel-shapira-4669ab104/"
  },
  {
    "href": "/in/moran-vitenberg-ben-ami-03739214b/"
  },
  {
    "href": "/in/sharon-eldar-33166b8/"
  },
  {
    "href": "/in/karin-weinberg-41522418/"
  },
  {
    "href": "/in/yuval-katz-580b0318/"
  },
  {
    "href": "/in/danielle-wienberger-b0b266142/"
  },
  {
    "href": "/in/mor-ksheshiver-b25310125/"
  },
  {
    "href": "/in/gal-galaska-rahamim-38a71637/"
  },
  {
    "href": "/in/rony-friedman-61034a9b/"
  },
  {
    "href": "/in/mor-eyal-80b81323/"
  },
  {
    "href": "/in/ifat-chen-cohen-17842a113/"
  },
  {
    "href": "/in/liatnaor/"
  },
  {
    "href": "/in/ravit-erlichman-you-should-join-us-b4bb8568/"
  },
  {
    "href": "/in/lital-levi/"
  },
  {
    "href": "/in/tzipi-abu-b252b2112/"
  },
  {
    "href": "/in/sharon-turgeman-thomas-57aa1514b/"
  },
  {
    "href": "/in/adishachar/"
  },
  {
    "href": "/in/oshrat-alterescu-a0092770/"
  },
  {
    "href": "/in/noy-zandberg-a655a6179/"
  },
  {
    "href": "/in/noa-berglas-13b20568/"
  },
  {
    "href": "/in/tal-lev-561ab046/"
  },
  {
    "href": "/in/merav-lahat-pasha-b5a9881a/"
  },
  {
    "href": "/in/ilana-shtikan-691bb169/"
  },
  {
    "href": "/in/rami-joseph-430972/"
  },
  {
    "href": "/in/ifatmeshulam/"
  },
  {
    "href": "/in/nadav-alon-1225b214/"
  },
  {
    "href": "/in/miri-sayag-64714411/"
  },
  {
    "href": "/in/inon-bookobza-30a138178/"
  },
  {
    "href": "/in/sarah-rapoport-9b30b287/"
  },
  {
    "href": "/in/danaprimo/"
  },
  {
    "href": "/in/mor-yeger-21796553/"
  },
  {
    "href": "/in/or-takser-moore-4b840199/"
  },
  {
    "href": "/in/racheli-dadon-67814963/"
  },
  {
    "href": "/in/einat-givoni-startica-i-m-hiring-7290b192/"
  },
  {
    "href": "/in/irena-rahmani-91a39154/"
  },
  {
    "href": "/in/lital-boostani-07b4b7178/"
  },
  {
    "href": "/in/tom-greenbaum-5b13a52b/"
  },
  {
    "href": "/in/hadas-harel-a1099514/"
  },
  {
    "href": "/in/neta-biller-23493121/"
  },
  {
    "href": "/in/shanihadar/"
  },
  {
    "href": "/in/alonabentzur/"
  },
  {
    "href": "/in/yosi-gold-31448b113/"
  },
  {
    "href": "/in/reut-naim-%D7%A8%D7%A2%D7%95%D7%AA-%D7%A0%D7%A2%D7%99%D7%9D-24984192/"
  },
  {
    "href": "/in/yelena-sigal-b4073848/"
  },
  {
    "href": "/in/sofia-kvacha/"
  },
  {
    "href": "/in/yaffaatiya/"
  },
  {
    "href": "/in/shimrit-nahmany-37152183/"
  },
  {
    "href": "/in/elranmillo/"
  },
  {
    "href": "/in/dudu-artzi/"
  },
  {
    "href": "/in/inbal-harel-377b19152/"
  },
  {
    "href": "/in/sandra-ilani-2b41a321/"
  },
  {
    "href": "/in/gohire-placement/"
  },
  {
    "href": "/in/liatkling/"
  },
  {
    "href": "/in/naomi-aldes-%D7%A0%D7%A2%D7%9E%D7%99-%D7%90%D7%9C%D7%93%D7%A1-7b4030120/"
  },
  {
    "href": "/in/michal-ben-ami/"
  },
  {
    "href": "/in/ortal-semidubersky-35757b119/"
  },
  {
    "href": "/in/gefen-lustig-5a782a45/"
  },
  {
    "href": "/in/ofri-shifman/"
  },
  {
    "href": "/in/tamar-rubanenko-bb5901149/"
  },
  {
    "href": "/in/jessica-hyman-4097b8145/"
  },
  {
    "href": "/in/diklashabi/"
  },
  {
    "href": "/in/yaara-gavriely-b92b8456/"
  },
  {
    "href": "/in/liza-goldis-perplotsik-60a68879/"
  },
  {
    "href": "/in/limor-gamzo-b31004ba/"
  },
  {
    "href": "/in/shirimarkovitz/"
  },
  {
    "href": "/in/shelly-kataby/"
  },
  {
    "href": "/in/tslil-shemesh-%E2%98%85-i-m-hiring-%E2%98%85-a192a8a4/"
  },
  {
    "href": "/in/deborah-abergel-magini-2a1b729a/"
  },
  {
    "href": "/in/rayashaulov/"
  },
  {
    "href": "/in/liron-fialkov/"
  },
  {
    "href": "/in/michal-levin-ben-yossef/"
  },
  {
    "href": "/in/liat-berko-559a88a3/"
  },
  {
    "href": "/in/ira-briker-gorelik-731840119/"
  },
  {
    "href": "/in/anna-burshtein-2b367513a/"
  },
  {
    "href": "/in/hofitmalki/"
  },
  {
    "href": "/in/vardit/"
  },
  {
    "href": "/in/moranyad/"
  },
  {
    "href": "/in/dorin-siman-tov-5329a2b8/"
  },
  {
    "href": "/in/liat-meisner-13b7b793/"
  },
  {
    "href": "/in/yana-kuryliuk-a0613aa2/"
  },
  {
    "href": "/in/emilymishkal/"
  },
  {
    "href": "/in/chen-kredo-336450148/"
  },
  {
    "href": "/in/mor-leshem-a0622a19/"
  },
  {
    "href": "/in/liat-fridman-5a114732/"
  },
  {
    "href": "/in/ronicon/"
  },
  {
    "href": "/in/noa-kind-084146153/"
  },
  {
    "href": "/in/shir-rintsler-eden-825b676a/"
  },
  {
    "href": "/in/ira-iozsef-a1a8543/"
  },
  {
    "href": "/in/noa-barel-846b2b83/"
  },
  {
    "href": "/in/rotem-lior-3264b1139/"
  },
  {
    "href": "/in/revitalab/"
  },
  {
    "href": "/in/inbar-zilberberg-hr/"
  },
  {
    "href": "/in/sharon-elias-820a39119/"
  },
  {
    "href": "/in/nili-morad-sabach/"
  },
  {
    "href": "/in/moran-hubesh-3b03783a/"
  },
  {
    "href": "/in/ilana-kushnir-21756819b/"
  },
  {
    "href": "/in/avishag-alaluf-623a0964/"
  },
  {
    "href": "/in/keren-shriker-50899293/"
  },
  {
    "href": "/in/yaara-yakolev-0444052b/"
  },
  {
    "href": "/in/rony-avni-levite-57b91549/"
  },
  {
    "href": "/in/galitbaresi/"
  },
  {
    "href": "/in/annazilberman/"
  },
  {
    "href": "/in/anne-lederman-368291b9/"
  },
  {
    "href": "/in/marinbass/"
  },
  {
    "href": "/in/tal-trosman-a550b473/"
  },
  {
    "href": "/in/nira-roth-7824941a/"
  },
  {
    "href": "/in/keren-yoffe-shvarzman-startica-i-m-hiring-300197163/"
  },
  {
    "href": "/in/zohar-lavy-b05695101/"
  },
  {
    "href": "/in/liron-shalom-4ba309143/"
  },
  {
    "href": "/in/galitminkin/"
  },
  {
    "href": "/in/gal-friedler-%E2%9C%AAlet-s-connect%E2%9C%AA-216537a4/"
  },
  {
    "href": "/in/gali-yosipov-884361189/"
  },
  {
    "href": "/in/yaarit-barmaimon-%E2%98%85i-m-hiring%E2%98%85-309b9831/"
  },
  {
    "href": "/in/ranit-gal-oz-96978323/"
  },
  {
    "href": "/in/sivanmenahem/"
  },
  {
    "href": "/in/shirley-toprecruiter/"
  },
  {
    "href": "/in/limor-cohen-83544b8/"
  },
  {
    "href": "/in/batel-zilbershmidt-84504183/"
  },
  {
    "href": "/in/adi-brayer-finkel-177b861/"
  },
  {
    "href": "/in/or-anaki-nitzan-382216142/"
  },
  {
    "href": "/in/israelson/"
  },
  {
    "href": "/in/naama-shemesh-nissel-679696a0/"
  },
  {
    "href": "/in/eva-gat-27911b116/"
  },
  {
    "href": "/in/amit-eshel-im-hiring-30547989/"
  },
  {
    "href": "/in/elinor-kneller-9394b4181/"
  },
  {
    "href": "/in/tamar-mazar-7649b7aa/"
  },
  {
    "href": "/in/carmit-kirnes-90545282/"
  },
  {
    "href": "/in/irit-even-haim-47715675/"
  },
  {
    "href": "/in/chen-amram/"
  },
  {
    "href": "/in/roie-almagor-ab8411146/"
  },
  {
    "href": "/in/lilachcarmely/"
  },
  {
    "href": "/in/shani-ushki-210043102/"
  },
  {
    "href": "/in/shira-beit-halachmi-cohen-bb585497/"
  },
  {
    "href": "/in/na-ama-raz-83a1a117/"
  },
  {
    "href": "/in/tammy-peres-keinan-47123728/"
  },
  {
    "href": "/in/keren-barak-8a72b0152/"
  }
]